{
  "type": "FeatureCollection", 
  "features": [
    {
      "geometry": {
        "type": "Polygon", 
        "coordinates": [
          [
            [
              106.375, 
              -7.821
            ], 
            [
              106.375, 
              -5.915
            ], 
            [
              108.840, 
              -5.915
            ], 
            [
              108.840, 
              -7.821
            ], 
            [
              106.375, 
              -7.821
            ]
          ]
        ]
      }, 
      "type": "Feature", 
      "properties": {
        "lang": "UNK", 
        "woeid": 2345715, 
        "name": "Jawa Barat", 
        "alias_ENG_P": [
          "West Java"
        ], 
        "ne_latitude": -5.915, 
        "provider": "geoplanet 7.6.0", 
        "ne_longitude": 108.840, 
        "longitude": 107.607, 
        "placetype": "State", 
        "adjacent_woeid": [
          2345713, 
          2345716, 
          28350158
        ], 
        "iso": "ID", 
        "date_indexed": "2010-12-02T16:52:36Z", 
        "parent_woeid": 23424846, 
        "latitude": -6.868, 
        "sw_longitude": 106.375, 
        "fullname": "Jawa Barat, West Java, Indonesia", 
        "sw_latitude": -7.821
      }, 
      "id": 2345715
    }
  ]
}