{
  "type": "FeatureCollection", 
  "features": [
    {
      "geometry": {
        "type": "Polygon", 
        "coordinates": [
          [
            [
              6.167, 
              49.459
            ], 
            [
              6.167, 
              49.86
            ], 
            [
              6.531, 
              49.86
            ], 
            [
              6.531, 
              49.459
            ], 
            [
              6.167, 
              49.459
            ]
          ]
        ]
      }, 
      "type": "Feature", 
      "properties": {
        "lang": "FRE", 
        "adjacent_woeid": [
          2345488, 
          2345489, 
          7153322, 
          20070542, 
          20070560
        ], 
        "name": "Grevenmacher", 
        "hierarchy": [
          "woe:state=20070559", 
          "woe:country=23424881", 
          "woe:planet=1"
        ], 
        "provider": "geoplanet 7.6.0", 
        "ne_longitude": 6.531, 
        "longitude": 6.349, 
        "placetype": "state", 
        "iso": "LU", 
        "sw_latitude": 49.459, 
        "adjacent": [
          "woe:state=20070542", 
          "woe:state=7153322", 
          "woe:state=20070560", 
          "woe:state=2345488", 
          "woe:state=2345489"
        ], 
        "ne_latitude": 49.86, 
        "latitude": 49.66, 
        "sw_longitude": 6.167, 
        "fullname": "Grevenmacher, Luxembourg", 
        "children": [
          "woe:county=12591967", 
          "woe:county=12591958", 
          "woe:county=12592004"
        ], 
        "date_indexed": "2010-12-02T08:54:13Z", 
        "woe:id": 20070559
      }, 
      "id": 20070559
    }
  ], 
  "bbox": [
    6.167, 
    49.459, 
    6.531, 
    49.86
  ]
}