{
  "type": "FeatureCollection", 
  "features": [
    {
      "geometry": {
        "type": "Polygon", 
        "coordinates": [
          [
            [
              47.824, 
              39.51
            ], 
            [
              47.824, 
              40.172
            ], 
            [
              48.345, 
              40.172
            ], 
            [
              48.345, 
              39.51
            ], 
            [
              47.824, 
              39.51
            ]
          ]
        ]
      }, 
      "type": "Feature", 
      "properties": {
        "lang": "ENG", 
        "adjacent_woeid": [
          20070198, 
          20070236, 
          20070242, 
          20070243, 
          20070256, 
          20070257, 
          20070281
        ], 
        "name": "Imisli", 
        "hierarchy": [
          "woe:state=20070227", 
          "woe:country=23424741", 
          "woe:planet=1"
        ], 
        "provider": "geoplanet 7.6.0", 
        "ne_longitude": 48.345, 
        "longitude": 48.085, 
        "placetype": "state", 
        "iso": "AZ", 
        "sw_latitude": 39.51, 
        "adjacent": [
          "woe:state=20070198", 
          "woe:state=20070257", 
          "woe:state=20070242", 
          "woe:state=20070236", 
          "woe:state=20070243", 
          "woe:state=20070281", 
          "woe:state=20070256"
        ], 
        "ne_latitude": 40.172, 
        "latitude": 39.841, 
        "sw_longitude": 47.824, 
        "fullname": "Imisli, Azerbaijan", 
        "children": [
          "woe:town=1948178", 
          "woe:town=1951912", 
          "woe:town=1949121"
        ], 
        "date_indexed": "2010-12-02T08:58:29Z", 
        "woe:id": 20070227
      }, 
      "id": 20070227
    }
  ], 
  "bbox": [
    47.824, 
    39.51, 
    48.345, 
    40.172
  ]
}