{
  "type": "FeatureCollection", 
  "features": [
    {
      "type": "Feature", 
      "properties": {
        "lang": "UNK", 
        "adjacent_woeid": [
          55844641, 
          20070118, 
          56190520, 
          56190523, 
          56190578, 
          56190540
        ], 
        "name": "Grobi\u0144as Novads", 
        "alias_UNK_S": [
          "Grobinas Novads"
        ], 
        "parent_woeid": 23424874, 
        "provider": "geoplanet 7.6.0", 
        "placetype": "State", 
        "iso": "LV", 
        "woeid": 56190577, 
        "date_indexed": "2010-12-02T08:49:33Z"
      }, 
      "id": 56190577
    }
  ]
}