{
  "type": "FeatureCollection", 
  "features": [
    {
      "geometry": {
        "type": "Polygon", 
        "coordinates": [
          [
            [
              -4.977, 
              6.181
            ], 
            [
              -4.977, 
              8.061
            ], 
            [
              -3.503, 
              8.061
            ], 
            [
              -3.503, 
              6.181
            ], 
            [
              -4.977, 
              6.181
            ]
          ]
        ]
      }, 
      "type": "Feature", 
      "properties": {
        "lang": "FRE", 
        "adjacent_woeid": [
          55966991, 
          55966997, 
          55967000, 
          55967005, 
          55967007, 
          55967009
        ], 
        "name": "N'zi-Como\u00e9", 
        "ne_latitude": 8.061, 
        "hierarchy": [
          "woe:state=55967001", 
          "woe:country=23424854", 
          "woe:planet=1"
        ], 
        "ne_longitude": -3.503, 
        "longitude": -4.24, 
        "alias_FRE_S": [
          "N'zi-Comoe"
        ], 
        "placetype": "state", 
        "iso": "CI", 
        "date_indexed": "2010-12-02T09:35:13Z", 
        "adjacent": [
          "woe:state=55966991", 
          "woe:state=55966997", 
          "woe:state=55967009", 
          "woe:state=55967000", 
          "woe:state=55967005", 
          "woe:state=55967007"
        ], 
        "provider": "geoplanet 7.6.0", 
        "latitude": 7.121, 
        "sw_longitude": -4.977, 
        "fullname": "N'zi-Como\u00e9, Ivory Coast", 
        "children": [
          "woe:county=56042280", 
          "woe:county=20069810", 
          "woe:county=20069982", 
          "woe:county=20069981", 
          "woe:county=20069986"
        ], 
        "sw_latitude": 6.181, 
        "woe:id": 55967001
      }, 
      "id": 55967001
    }
  ], 
  "bbox": [
    -4.977, 
    6.181, 
    -3.503, 
    8.061
  ]
}