{
  "type": "FeatureCollection", 
  "features": [
    {
      "geometry": {
        "type": "Polygon", 
        "coordinates": [
          [
            [
              4.889, 
              47.813
            ], 
            [
              4.889, 
              49.618
            ], 
            [
              7.640, 
              49.618
            ], 
            [
              7.640, 
              47.813
            ], 
            [
              4.889, 
              47.813
            ]
          ]
        ]
      }, 
      "type": "Feature", 
      "properties": {
        "alias_SWE_Q": [
          "Lothringen"
        ], 
        "ne_latitude": 49.618, 
        "placetype": "State", 
        "alias_POR_Q": [
          "Lorena"
        ], 
        "alias_KOR_Q": [
          "\ub85c\ub80c"
        ], 
        "alias_CHI_Q": [
          "\u6d1b\u6797"
        ], 
        "alias_ITA_Q": [
          "Lorena"
        ], 
        "woeid": 7153322, 
        "alias_JPN_Q": [
          "\u30ed\u30ec\u30fc\u30cc"
        ], 
        "alias_SPA_Q": [
          "Lorena"
        ], 
        "alias_FIN_Q": [
          "Lothringen"
        ], 
        "sw_longitude": 4.889, 
        "provider": "geoplanet 7.6.0", 
        "latitude": 48.715, 
        "date_indexed": "2010-12-02T11:51:35Z", 
        "alias_DUT_Q": [
          "Lotharingen"
        ], 
        "alias_GER_Q": [
          "Lothringen"
        ], 
        "lang": "FRE", 
        "adjacent_woeid": [
          2345488, 
          2345489, 
          7153302, 
          7153315, 
          7153317, 
          7153330, 
          20070559, 
          20070560
        ], 
        "name": "Lorraine", 
        "parent_woeid": 23424819, 
        "ne_longitude": 7.640, 
        "longitude": 6.264, 
        "iso": "FR", 
        "sw_latitude": 47.813, 
        "alias_FRE_V": [
          "Lorraine Region"
        ], 
        "fullname": "Lorraine, France"
      }, 
      "id": 7153322
    }
  ]
}