{
  "type": "FeatureCollection", 
  "features": [
    {
      "geometry": {
        "type": "Polygon", 
        "coordinates": [
          [
            [
              13.607327041909514, 
              14.51843929084066
            ], 
            [
              13.615324334250658, 
              14.516530259463934
            ], 
            [
              13.721622755785575, 
              14.516995347457396
            ], 
            [
              13.735575391990778, 
              14.51570343716395
            ], 
            [
              13.747822706752572, 
              14.512912909203465
            ], 
            [
              13.760741815082724, 
              14.502164211209447
            ], 
            [
              13.770663689877438, 
              14.488418280579253
            ], 
            [
              13.777795037610929, 
              14.480718492064796
            ], 
            [
              13.784926385344477, 
              14.47637767139247
            ], 
            [
              13.950497674128428, 
              14.466145738235298
            ], 
            [
              13.99581790517226, 
              14.452348130761663
            ], 
            [
              14.008065219933997, 
              14.434674790609165
            ], 
            [
              14.012095981344487, 
              14.431057440348638
            ], 
            [
              14.017366978003679, 
              14.428060207712463
            ], 
            [
              14.026358676811526, 
              14.426561590944743
            ], 
            [
              14.061446974698185, 
              14.425631414957877
            ], 
            [
              14.073694288560603, 
              14.424029446301972
            ], 
            [
              14.08020551956912, 
              14.421290595184871
            ], 
            [
              14.08733686730261, 
              14.416691392094094
            ], 
            [
              14.10506188339923, 
              14.39354035060677
            ], 
            [
              14.109092644809778, 
              14.391008205963999
            ], 
            [
              14.11529381655646, 
              14.391421617113963
            ], 
            [
              14.12165001793403, 
              14.390181382764638
            ], 
            [
              14.127076043324791, 
              14.386719062135057
            ], 
            [
              14.131881951990522, 
              14.378347480052184
            ], 
            [
              14.134207391058283, 
              14.371474513837768
            ], 
            [
              14.141028680429315, 
              14.328686428336027
            ], 
            [
              14.145679558564836, 
              14.313855292088135
            ], 
            [
              14.149400262512131, 
              14.308480943540758
            ], 
            [
              14.156273227827228, 
              14.303520006143401
            ], 
            [
              14.190224643252748, 
              14.286156724353418
            ], 
            [
              14.24825727705172, 
              14.224041653199777
            ], 
            [
              14.26174482616284, 
              14.213189602418254
            ], 
            [
              14.307375115569187, 
              14.198823554163766
            ], 
            [
              14.318847283975003, 
              14.186472886614467
            ], 
            [
              14.346959262859741, 
              14.145648504974588
            ], 
            [
              14.356571079291939, 
              14.134951483823954
            ], 
            [
              14.36773318843592, 
              14.130197252001608
            ], 
            [
              14.376104770518793, 
              14.128285224083868
            ], 
            [
              14.442095574351299, 
              14.121722317131287
            ], 
            [
              14.453567742757173, 
              14.118828436383296
            ], 
            [
              14.46410973517618, 
              14.115107733335265
            ], 
            [
              14.470155877291973, 
              14.110973619137269
            ], 
            [
              14.477442254656353, 
              14.104514064972193
            ], 
            [
              14.565137160051961, 
              13.987208563924128
            ], 
            [
              14.576454298826889, 
              13.97470286674394
            ], 
            [
              14.616038446117443, 
              13.941113186524376
            ], 
            [
              14.643788689796224, 
              13.908918768486444
            ], 
            [
              14.795717400737487, 
              13.67120718006737
            ], 
            [
              14.805174187538796, 
              13.663817450814747
            ], 
            [
              14.815716179957803, 
              13.6683133002187
            ], 
            [
              14.839642367801105, 
              13.685883286684373
            ], 
            [
              14.850959506576032, 
              13.687640285870543
            ], 
            [
              14.858245883940413, 
              13.687536933083038
            ], 
            [
              14.907596876394791, 
              13.678235175013356
            ], 
            [
              14.915813429746038, 
              13.678751938950882
            ], 
            [
              15.213262973407552, 
              13.750582180223489
            ], 
            [
              15.716178012405408, 
              13.754923000895815
            ], 
            [
              15.721965773002069, 
              13.756990057545181
            ], 
            [
              15.726099888099384, 
              13.759987291080677
            ], 
            [
              15.748475783230845, 
              13.786652330041022
            ], 
            [
              15.752351515010446, 
              13.78954620988975
            ], 
            [
              15.758242628394612, 
              13.790166327514044
            ], 
            [
              15.764133741778835, 
              13.789597886733134
            ], 
            [
              15.775450880553763, 
              13.786548977253574
            ], 
            [
              15.796276482973383, 
              13.778694159108227
            ], 
            [
              15.819840935610728, 
              13.773113104985839
            ], 
            [
              15.841751743648103, 
              13.765775051677338
            ], 
            [
              15.847332797770434, 
              13.762209377360932
            ], 
            [
              15.852603794429626, 
              13.756886704757676
            ], 
            [
              15.857409702196037, 
              13.745104477989344
            ], 
            [
              15.861440463606584, 
              13.730273342640714
            ], 
            [
              15.865316196285505, 
              13.707173977097398
            ], 
            [
              15.86500613792299, 
              13.700921128507332
            ], 
            [
              15.859890170894744, 
              13.68815704980807
            ], 
            [
              15.841596714017214, 
              13.65653107345031
            ], 
            [
              15.840046421305374, 
              13.650123196128675
            ], 
            [
              15.840201450036943, 
              13.642630113189227
            ], 
            [
              15.85074344245595, 
              13.608988756126223
            ], 
            [
              15.853378940785547, 
              13.59544953017172
            ], 
            [
              15.858184848551957, 
              13.581238511548122
            ], 
            [
              15.860510288519038, 
              13.576846014931675
            ], 
            [
              15.8698120456894, 
              13.565270493738353
            ], 
            [
              15.890947706471536, 
              13.543773097750318
            ], 
            [
              15.896528761493187, 
              13.53550486935427
            ], 
            [
              15.898389113466862, 
              13.521500556305682
            ], 
            [
              15.899939406178703, 
              13.2504576682868
            ], 
            [
              15.896993849486591, 
              13.22678986286195
            ], 
            [
              15.883609653163035, 
              13.18787750913981
            ], 
            [
              15.871672397663076, 
              13.17149608018002
            ], 
            [
              15.84764285613295, 
              13.16875722906292
            ], 
            [
              15.776226026909683, 
              13.17185781538592
            ], 
            [
              15.743049757840083, 
              13.182141425386533
            ], 
            [
              15.441052687031913, 
              13.318670559298937
            ], 
            [
              15.432216016955692, 
              13.324044907846258
            ], 
            [
              15.414232618440622, 
              13.341098130374462
            ], 
            [
              15.402140333309774, 
              13.356601060190826
            ], 
            [
              15.378369175097419, 
              13.39577179633136
            ], 
            [
              15.374493442418498, 
              13.400215968891928
            ], 
            [
              15.36813724104087, 
              13.404970200714217
            ], 
            [
              15.356820102265942, 
              13.405125230345163
            ], 
            [
              15.229902784785736, 
              13.381405748076872
            ], 
            [
              15.219050734004213, 
              13.377788397816346
            ], 
            [
              15.214503207756877, 
              13.372414048369706
            ], 
            [
              15.219464145154234, 
              13.361406968856556
            ], 
            [
              15.30591881709978, 
              13.241052557429612
            ], 
            [
              15.30917443215435, 
              13.23795197200593
            ], 
            [
              15.313360223195787, 
              13.235213120888886
            ], 
            [
              15.318166130962197, 
              13.2331460633402
            ], 
            [
              15.366741977959975, 
              13.223689276538948
            ], 
            [
              15.37201297371979, 
              13.221828925464592
            ], 
            [
              15.375733676767823, 
              13.218521633566581
            ], 
            [
              15.378214145466472, 
              13.214180812894256
            ], 
            [
              15.38317508286383, 
              13.198781235865397
            ], 
            [
              15.383485141226345, 
              13.19366526973647
            ], 
            [
              15.382089878145393, 
              13.188859361070683
            ], 
            [
              15.379299351084228, 
              13.185035305235203
            ], 
            [
              15.327984652969405, 
              13.144159247651203
            ], 
            [
              15.322661981265469, 
              13.141317043746596
            ], 
            [
              15.318941277318117, 
              13.142092190102517
            ], 
            [
              15.311654900853057, 
              13.149791978616975
            ], 
            [
              15.3066939634557, 
              13.150722154603784
            ], 
            [
              15.301267938064939, 
              13.150205389766995
            ], 
            [
              15.293206414344581, 
              13.147414862705773
            ], 
            [
              15.2901058289209, 
              13.146071275568943
            ], 
            [
              15.286540154604495, 
              13.143694159657798
            ], 
            [
              15.283904656274899, 
              13.139663397347931
            ], 
            [
              15.282354363563059, 
              13.134134019169721
            ], 
            [
              15.28049401248876, 
              13.121679998832917
            ], 
            [
              15.278478630884138, 
              13.11522044556716
            ], 
            [
              15.275688103822972, 
              13.10886424418959
            ], 
            [
              15.269900343226311, 
              13.102042954818558
            ], 
            [
              15.264629347466439, 
              13.100492662106717
            ], 
            [
              15.259513380438193, 
              13.101216131619253
            ], 
            [
              15.255327589396757, 
              13.103903306792233
            ], 
            [
              15.251606886348782, 
              13.107210597790925
            ], 
            [
              15.24866132965667, 
              13.11113800731323
            ], 
            [
              15.245870802595505, 
              13.11537547429873
            ], 
            [
              15.238584425231068, 
              13.135374253519046
            ], 
            [
              15.235483839807387, 
              13.139249986197967
            ], 
            [
              15.231608107128466, 
              13.142350572520968
            ], 
            [
              15.227422316087086, 
              13.145192775526198
            ], 
            [
              15.223701613039054, 
              13.14855174426765
            ], 
            [
              15.218120558017404, 
              13.156716620775455
            ], 
            [
              15.214193149394362, 
              13.159920558986641
            ], 
            [
              15.18969852077015, 
              13.171186021817505
            ], 
            [
              15.18551272972877, 
              13.17376984330366
            ], 
            [
              15.18256717303666, 
              13.177077134302351
            ], 
            [
              15.182102085043255, 
              13.181676337393128
            ], 
            [
              15.182257114674144, 
              13.19268341690622
            ], 
            [
              15.180396762700468, 
              13.197230943153556
            ], 
            [
              15.177761264370929, 
              13.201054998989036
            ], 
            [
              15.174040561322897, 
              13.203742174162073
            ], 
            [
              15.169544711918945, 
              13.206067613229834
            ], 
            [
              15.135386590019152, 
              13.218004868729736
            ], 
            [
              15.105155877641664, 
              13.223482570963938
            ], 
            [
              15.095337355634513, 
              13.226583156387619
            ], 
            [
              15.088206007901022, 
              13.229787095498125
            ], 
            [
              15.084020216859585, 
              13.23252594661517
            ], 
            [
              15.079059279462228, 
              13.234748032895425
            ], 
            [
              15.073633254071467, 
              13.23640167929409
            ], 
            [
              15.06154096894062, 
              13.238778795205292
            ], 
            [
              15.040405307259164, 
              13.246323554088804
            ], 
            [
              15.024592319080284, 
              13.253868312972315
            ], 
            [
              15.00428348149751, 
              13.260069484718997
            ], 
            [
              14.996635369826492, 
              13.259656073568976
            ], 
            [
              14.991209344435731, 
              13.257485663232842
            ], 
            [
              14.988573846106135, 
              13.253248196247284
            ], 
            [
              14.98810875811273, 
              13.247873846800644
            ], 
            [
              14.989504022093001, 
              13.242912909403287
            ], 
            [
              14.994154901127843, 
              13.233766180964551
            ], 
            [
              14.998082309750828, 
              13.224309394163242
            ], 
            [
              15.001647983167913, 
              13.206997789216643
            ], 
            [
              15.00257815915478, 
              13.18823924434571
            ], 
            [
              15.00412845186662, 
              13.182968247686517
            ], 
            [
              15.007229038189621, 
              13.178989162220091
            ], 
            [
              15.015135532279032, 
              13.17278799047341
            ], 
            [
              15.018701205696118, 
              13.169222317056324
            ], 
            [
              15.021801792019119, 
              13.165088201959009
            ], 
            [
              15.02412723108688, 
              13.160488999767551
            ], 
            [
              15.04226565923284, 
              13.103644924373782
            ], 
            [
              15.043195835219649, 
              13.097960516564626
            ], 
            [
              15.04304080558876, 
              13.09186269760545
            ], 
            [
              15.037769809828887, 
              13.069073391324025
            ], 
            [
              15.023817172724364, 
              13.033416652656456
            ], 
            [
              15.017460971346793, 
              13.00980052317567
            ], 
            [
              15.014050327560597, 
              13.003340969010537
            ], 
            [
              15.007229038189621, 
              13.000963853099393
            ], 
            [
              14.998392368113343, 
              12.999826971537573
            ], 
            [
              14.50090335450625, 
              13.001480617936238
            ], 
            [
              14.48086951701464, 
              13.000499578992446
            ], 
            [
              14.48085289844255, 
              13.000498765105988
            ], 
            [
              14.435015903461249, 
              13.070572008091744
            ], 
            [
              14.417807651302098, 
              13.081372382029883
            ], 
            [
              14.064547560121866, 
              13.078271795706883
            ], 
            [
              13.606952752167842, 
              13.704383450036232
            ], 
            [
              13.481895785761935, 
              14.260008449330542
            ], 
            [
              13.448874546323282, 
              14.38041453670155
            ], 
            [
              13.449236280629918, 
              14.439325669644006
            ], 
            [
              13.481895785761935, 
              14.483870754331917
            ], 
            [
              13.507475620003902, 
              14.49622142188116
            ], 
            [
              13.543390740190546, 
              14.510845852554098
            ], 
            [
              13.58395674031135, 
              14.514049790765284
            ], 
            [
              13.607314487373742, 
              14.518442287381731
            ], 
            [
              13.607327041909514, 
              14.51843929084066
            ]
          ]
        ]
      }, 
      "type": "Feature", 
      "properties": {
        "ne:ProvNumber": 13, 
        "ne:ScaleRank": 4, 
        "ne:woe:id": "2344951", 
        "adjacent_woeid": [
          2344950, 
          56013481
        ], 
        "ne_latitude": 14.518442287381731, 
        "ne:Shape_Area": 1.92564989047, 
        "placetype": "State", 
        "ne:Country_Pr": null, 
        "ne:VALIDFR_1": "19621029", 
        "ne:gadm_level": 1.0, 
        "ne:ADM0_A3": "TCD", 
        "ne:DataRank": 7, 
        "ne:Abbrev": null, 
        "ne:VALIDTO_1": "Unknown", 
        "sw_longitude": 13.448874546323282, 
        "provider": "geoplanet 7.6.0", 
        "latitude": 13.718, 
        "ne:FIPS_1": "CD07", 
        "ne:FIRST_FIPS": null, 
        "ne:FIRST_HASC": null, 
        "ne:ENGTYPE_1": "Prefecture", 
        "sw_latitude": 12.999826971537573, 
        "lang": "FRE", 
        "ne:MAP_COLOR": 6, 
        "ne:OBJECTID": 1466, 
        "ne:Postal": "LC", 
        "ne:Region_Cod": null, 
        "ne:VARNAME_1": null, 
        "ne:ISO": "TCD", 
        "ne:TYPE_1": "Pr\u00e9fecture", 
        "ne:Region_C_2": null, 
        "ne:Shape_Leng": 7.79705327811, 
        "ne:CheckMe": 0, 
        "ne:NAME_0": "Chad", 
        "ne:NAME_1": "Lac", 
        "ne:Region_C_1": null, 
        "ne:Region_C_3": null, 
        "ne:LabelRank": 4, 
        "ne:Area_sqkm": 23050.8, 
        "woe:id": "2344951", 
        "name": "Lac", 
        "ne:VertexCou": 202.0, 
        "ne:NL_NAME_1": null, 
        "ne:HASC_1": "TD.LC", 
        "ne:REMARKS_1": null, 
        "parent_woeid": 23424777, 
        "ne_longitude": 15.899939406178703, 
        "longitude": 14.701, 
        "alias_FRE_A": [
          "LC"
        ], 
        "iso": "TD", 
        "date_indexed": "2010-12-02T08:53:18Z", 
        "fullname": "Lac, Chad", 
        "ne:Region": null, 
        "ne:NEV_Countr": "Chad", 
        "ne:RegionVar": null, 
        "ne:sameAsCity": -99
      }, 
      "id": 2344951
    }
  ], 
  "bbox": [
    13.448874546323282, 
    12.999826971537573, 
    15.899939406178703, 
    14.518442287381731
  ]
}