{
  "type": "FeatureCollection", 
  "features": [
    {
      "geometry": {
        "type": "Polygon", 
        "coordinates": [
          [
            [
              -57.618, 
              -33.751
            ], 
            [
              -57.618, 
              -27.080
            ], 
            [
              -49.691, 
              -27.080
            ], 
            [
              -49.691, 
              -33.751
            ], 
            [
              -57.618, 
              -33.751
            ]
          ]
        ]
      }, 
      "type": "Feature", 
      "properties": {
        "lang": "POR", 
        "woeid": 2344864, 
        "name": "Rio Grande do Sul", 
        "adjacent_woeid": [
          2344680, 
          2344688, 
          2344867, 
          2347640, 
          2347642, 
          2347652, 
          2347653, 
          2347658
        ], 
        "ne_latitude": -27.080, 
        "provider": "geoplanet 7.6.0", 
        "ne_longitude": -49.691, 
        "longitude": -53.655, 
        "placetype": "State", 
        "alias_POR_V": [
          "Riograndedosul"
        ], 
        "iso": "BR", 
        "date_indexed": "2010-12-02T17:58:27Z", 
        "alias_ENG_A": [
          "RS"
        ], 
        "parent_woeid": 23424768, 
        "latitude": -30.415, 
        "sw_longitude": -57.618, 
        "fullname": "Rio Grande do Sul, Brazil", 
        "sw_latitude": -33.751
      }, 
      "id": 2344864
    }
  ]
}