{
  "type": "FeatureCollection", 
  "features": [
    {
      "geometry": {
        "type": "Polygon", 
        "coordinates": [
          [
            [
              96.814, 
              18.492
            ], 
            [
              96.814, 
              19.999
            ], 
            [
              97.91, 
              19.999
            ], 
            [
              97.91, 
              18.492
            ], 
            [
              96.814, 
              18.492
            ]
          ]
        ]
      }, 
      "type": "Feature", 
      "properties": {
        "lang": "ENG", 
        "adjacent_woeid": [
          2344814, 
          2344820, 
          2347128
        ], 
        "name": "Kayan State", 
        "hierarchy": [
          "woe:state=2344815", 
          "woe:country=23424763", 
          "woe:planet=1"
        ], 
        "woeid": 2344815, 
        "ne_longitude": 97.91, 
        "longitude": 97.362, 
        "placetype": "state", 
        "latitude": 19.245, 
        "iso": "MM", 
        "sw_latitude": 18.492, 
        "adjacent": [
          "woe:state=2344814", 
          "woe:state=2347128", 
          "woe:state=2344820"
        ], 
        "provider": "geoplanet 7.6.0", 
        "ne_latitude": 19.999, 
        "sw_longitude": 96.814, 
        "fullname": "Kayan State, Myanmar", 
        "date_indexed": "2010-12-02T17:58:12Z"
      }, 
      "id": 2344815
    }
  ], 
  "bbox": [
    96.814, 
    18.492, 
    97.91, 
    19.999
  ]
}