{
  "type": "FeatureCollection", 
  "features": [
    {
      "geometry": {
        "type": "Polygon", 
        "coordinates": [
          [
            [
              25.075, 
              42.779
            ], 
            [
              25.075, 
              43.655
            ], 
            [
              26.173, 
              43.655
            ], 
            [
              26.173, 
              42.779
            ], 
            [
              25.075, 
              42.779
            ]
          ]
        ]
      }, 
      "type": "Feature", 
      "properties": {
        "lang": "ENG", 
        "woeid": 20070063, 
        "name": "Veliko Turnovo", 
        "adjacent_woeid": [
          2346648, 
          20070049, 
          20070054, 
          20070062, 
          20070064, 
          20070065, 
          20070069, 
          20070072
        ], 
        "ne_latitude": 43.655, 
        "provider": "geoplanet 7.6.0", 
        "alias_ENG_V": [
          "Veliko Tarnovo"
        ], 
        "ne_longitude": 26.173, 
        "longitude": 25.624, 
        "placetype": "State", 
        "iso": "BG", 
        "date_indexed": "2010-12-02T16:14:08Z", 
        "parent_woeid": 23424771, 
        "latitude": 43.217, 
        "sw_longitude": 25.075, 
        "fullname": "Veliko Turnovo, Bulgaria", 
        "sw_latitude": 42.779
      }, 
      "id": 20070063
    }
  ]
}