{
  "type": "FeatureCollection", 
  "features": [
    {
      "geometry": {
        "type": "Polygon", 
        "coordinates": [
          [
            [
              78.27525353342389, 
              47.304296373478905
            ], 
            [
              78.56205773277821, 
              47.19417389610845
            ], 
            [
              78.6398824402225, 
              47.145649725954115
            ], 
            [
              78.73662072126933, 
              47.13521108632261
            ], 
            [
              78.80462690580714, 
              47.06872935607498
            ], 
            [
              78.94839074113986, 
              47.057386379777654
            ], 
            [
              79.04461225824917, 
              47.06477610903028
            ], 
            [
              79.3084721207918, 
              47.03103139917977
            ], 
            [
              79.4914066913658, 
              46.862023627288636
            ], 
            [
              80.01871300620036, 
              46.879541937810245
            ], 
            [
              80.26706993982594, 
              46.81523061789875
            ], 
            [
              80.27130740771076, 
              46.77096975315163
            ], 
            [
              80.34954552630506, 
              46.736320705736034
            ], 
            [
              80.77949344246844, 
              46.591988430521724
            ], 
            [
              81.05492882710377, 
              46.5436709659424
            ], 
            [
              81.16685997960445, 
              46.54026032125688
            ], 
            [
              81.23300581216853, 
              46.515869045420175
            ], 
            [
              81.26101443916508, 
              46.490805976015054
            ], 
            [
              81.37325565002828, 
              46.493906561438735
            ], 
            [
              81.41004926935835, 
              46.47488963504867
            ], 
            [
              81.41408003166816, 
              46.44938731517249
            ], 
            [
              81.60476606670068, 
              46.39019196228929
            ], 
            [
              81.64755415220242, 
              46.31092031492062
            ], 
            [
              81.91348107319305, 
              46.0634935572819
            ], 
            [
              81.98355431527949, 
              45.90298655868281
            ], 
            [
              82.08453006421115, 
              45.80573151279913
            ], 
            [
              82.13972049320626, 
              45.68899445253203
            ], 
            [
              82.12504438658925, 
              45.58765696839441
            ], 
            [
              82.27459598161931, 
              45.54838288036569
            ], 
            [
              82.2967134952317, 
              45.55442902248143
            ], 
            [
              82.29113244020999, 
              45.533396714486855
            ], 
            [
              82.32709923724008, 
              45.49360586162129
            ], 
            [
              82.32709923724008, 
              45.49355418567717
            ], 
            [
              82.32730594281509, 
              45.49355418567717
            ], 
            [
              82.32740929560259, 
              45.493502508833785
            ], 
            [
              82.3622392110708, 
              45.48146190054632
            ], 
            [
              82.51272098208773, 
              45.46595897072996
            ], 
            [
              82.61524702373123, 
              45.43557322872158
            ], 
            [
              82.63168012863508, 
              45.416039537494726
            ], 
            [
              82.63602094930741, 
              45.37906505011205
            ], 
            [
              82.63354048060876, 
              45.33955841718728
            ], 
            [
              82.61411014216941, 
              45.24876292546867
            ], 
            [
              82.58486128082353, 
              45.177036037882885
            ], 
            [
              82.53947897857205, 
              45.12396968615212
            ], 
            [
              82.53938602104807, 
              45.12386098869371
            ], 
            [
              82.47551395070832, 
              45.115954494604296
            ], 
            [
              82.42714481018493, 
              45.13740021464827
            ], 
            [
              82.34146528549456, 
              45.2050963408235
            ], 
            [
              82.29412967284617, 
              45.22835073509839
            ], 
            [
              82.24493371002274, 
              45.23201976130298
            ], 
            [
              82.19139692562766, 
              45.22238210734844
            ], 
            [
              82.00009077387017, 
              45.153729966764615
            ], 
            [
              81.9498612813731, 
              45.14468659111333
            ], 
            [
              81.90976037014502, 
              45.15822581616851
            ], 
            [
              81.89053673728068, 
              45.17388377561582
            ], 
            [
              81.87503380746432, 
              45.181273504868386
            ], 
            [
              81.80692426923969, 
              45.18892161743872
            ], 
            [
              81.7933850441845, 
              45.19579458275382
            ], 
            [
              81.78811404842463, 
              45.20933380780906
            ], 
            [
              81.7868738140753, 
              45.232536526139825
            ], 
            [
              81.78108605347865, 
              45.266849676771244
            ], 
            [
              81.76475630046298, 
              45.30795827925124
            ], 
            [
              81.73891808470188, 
              45.33826650689383
            ], 
            [
              81.70439822759619, 
              45.340075182024066
            ], 
            [
              81.66491743399246, 
              45.3481367048451
            ], 
            [
              81.6222327003789, 
              45.3345458038458
            ], 
            [
              81.54581511357668, 
              45.295601281374104
            ], 
            [
              81.54197053341346, 
              45.29364197699567
            ], 
            [
              81.5417208186609, 
              45.29351471573159
            ], 
            [
              81.14381229000526, 
              45.20488963434917
            ], 
            [
              81.06216352762476, 
              45.172436835691485
            ], 
            [
              81.02154585155984, 
              45.16184316642904
            ], 
            [
              80.9756571797351, 
              45.16127472564813
            ], 
            [
              80.85359744686474, 
              45.12670319259831
            ], 
            [
              80.82713911347935, 
              45.12597972308578
            ], 
            [
              80.74528364462458, 
              45.14447988553832
            ], 
            [
              80.69670779852612, 
              45.14383393039162
            ], 
            [
              80.53640750550204, 
              45.10127838798729
            ], 
            [
              80.46716108571559, 
              45.106497707803044
            ], 
            [
              80.44505044292367, 
              45.10444090342503
            ], 
            [
              80.44494022021507, 
              45.10443065025436
            ], 
            [
              80.42671312431128, 
              45.093526941515165
            ], 
            [
              80.42488549417027, 
              45.092433626710545
            ], 
            [
              80.42468305857636, 
              45.09231252670179
            ], 
            [
              80.40599019838902, 
              45.05686322026145
            ], 
            [
              80.40597619054881, 
              45.05683665608689
            ], 
            [
              80.39781106852604, 
              45.0514104679188
            ], 
            [
              80.38987500202978, 
              45.04613649900028
            ], 
            [
              80.38964643753314, 
              45.045984605305364
            ], 
            [
              80.36463504407209, 
              45.04334910787509
            ], 
            [
              80.29011762852582, 
              45.04644969329877
            ], 
            [
              80.21849409372749, 
              45.0262442085035
            ], 
            [
              80.14718061729172, 
              45.034667466530436
            ], 
            [
              80.10294559096633, 
              45.03239370340674
            ], 
            [
              80.06148687162187, 
              45.019258267655005
            ], 
            [
              80.0611910342389, 
              45.01916453671407
            ], 
            [
              80.0233638852352, 
              44.99350718810632
            ], 
            [
              80.0233638852352, 
              44.99342967374048
            ], 
            [
              80.0072895360833, 
              44.98345653758918
            ], 
            [
              79.92424848827716, 
              44.931934719311926
            ], 
            [
              79.87773969882812, 
              44.914933173627105
            ], 
            [
              79.86864495030426, 
              44.909902787883425
            ], 
            [
              79.85779259645125, 
              44.90390025479297
            ], 
            [
              79.8424963722099, 
              44.873695379937885
            ], 
            [
              79.86823123608275, 
              44.849562486519574
            ], 
            [
              79.99122114493997, 
              44.79385529268768
            ], 
            [
              80.03897016783901, 
              44.79070302952124
            ], 
            [
              80.21777062331569, 
              44.81824656852439
            ], 
            [
              80.24433230948853, 
              44.8161795109757
            ], 
            [
              80.26283247284039, 
              44.809513251235614
            ], 
            [
              80.313992140425, 
              44.78049693478579
            ], 
            [
              80.47573937337341, 
              44.73561595331364
            ], 
            [
              80.49196577360163, 
              44.728174547217634
            ], 
            [
              80.4970300637865, 
              44.715100409256536
            ], 
            [
              80.49157903814216, 
              44.70193566909592
            ], 
            [
              80.4915523615523, 
              44.70187124256387
            ], 
            [
              80.47573937337341, 
              44.693913072530336
            ], 
            [
              80.41073042147184, 
              44.68306102174881
            ], 
            [
              80.37601546364277, 
              44.67155784022219
            ], 
            [
              80.37579715321613, 
              44.671485500555434
            ], 
            [
              80.35543663968923, 
              44.6530886908904
            ], 
            [
              80.35409305165308, 
              44.64197825769048
            ], 
            [
              80.35874393068792, 
              44.632779853307625
            ], 
            [
              80.37683068199044, 
              44.61551992430509
            ], 
            [
              80.38334191299896, 
              44.60301422802428
            ], 
            [
              80.37962120995093, 
              44.591542059618405
            ], 
            [
              80.36411828013456, 
              44.56983795805536
            ], 
            [
              80.33745324117422, 
              44.49418366184659
            ], 
            [
              80.33001183507821, 
              44.45325592741915
            ], 
            [
              80.33249230377686, 
              44.4176250271733
            ], 
            [
              80.37248986221744, 
              44.270398871211
            ], 
            [
              80.37269656779245, 
              44.23122813596973
            ], 
            [
              80.3456181167827, 
              44.15913951227873
            ], 
            [
              80.33848676994853, 
              44.12167409938024
            ], 
            [
              80.34468794169521, 
              44.10330312723761
            ], 
            [
              80.35936404831222, 
              44.089505519763975
            ], 
            [
              80.39192020065678, 
              44.06568268470818
            ], 
            [
              80.40339236816334, 
              44.04914622701682
            ], 
            [
              80.40959354080934, 
              44.03214468043274
            ], 
            [
              80.41197065582116, 
              44.01382538513349
            ], 
            [
              80.412280715083, 
              43.9935940619165
            ], 
            [
              80.412280715083, 
              43.99343903228555
            ], 
            [
              80.42271935381518, 
              43.97240672429092
            ], 
            [
              80.43946251798087, 
              43.949204006859475
            ], 
            [
              80.47573937337341, 
              43.910446681868905
            ], 
            [
              80.71231408112999, 
              43.45905304656088
            ], 
            [
              80.70973025874451, 
              43.42608348216703
            ], 
            [
              80.69391727056563, 
              43.39487091695929
            ], 
            [
              80.64244754461856, 
              43.32639964442808
            ], 
            [
              80.65805382722243, 
              43.31081920024593
            ], 
            [
              80.6955709169643, 
              43.30345530851571
            ], 
            [
              80.73494835778052, 
              43.2890375843171
            ], 
            [
              80.74807417168574, 
              43.27534332963103
            ], 
            [
              80.75551557778175, 
              43.25782501910942
            ], 
            [
              80.75871951689226, 
              43.23844635661413
            ], 
            [
              80.75954634009156, 
              43.21896434223066
            ], 
            [
              80.76481733585143, 
              43.20015412051629
            ], 
            [
              80.7877616717638, 
              43.16845062889348
            ], 
            [
              80.79303266842294, 
              43.149666246500146
            ], 
            [
              80.78745161340129, 
              43.12816885051211
            ], 
            [
              80.77304863808422, 
              43.11314860392497
            ], 
            [
              80.7729822123593, 
              43.11307933184577
            ], 
            [
              80.7530351090831, 
              43.10419098582537
            ], 
            [
              80.73112430194504, 
              43.10129710507738
            ], 
            [
              80.71035037636881, 
              43.10501780902473
            ], 
            [
              80.65960411993427, 
              43.13297475827852
            ], 
            [
              80.61805626788254, 
              43.1344733750463
            ], 
            [
              80.57547488795575, 
              43.119538886010844
            ], 
            [
              80.49744347493646, 
              43.07633738845976
            ], 
            [
              80.4098002463843, 
              43.048845526300056
            ], 
            [
              80.36792423261733, 
              43.0287820804287
            ], 
            [
              80.36773563039509, 
              43.02869171834817
            ], 
            [
              80.35471316927737, 
              43.00073476819506
            ], 
            [
              80.37331668451742, 
              42.97541331637149
            ], 
            [
              80.40731977768564, 
              42.95494944915782
            ], 
            [
              80.47573937337341, 
              42.930506496477676
            ], 
            [
              80.52152469241071, 
              42.92559723592376
            ], 
            [
              80.54250532446122, 
              42.91683808021327
            ], 
            [
              80.55408084475522, 
              42.89911306411665
            ], 
            [
              80.54820107092274, 
              42.87871437616758
            ], 
            [
              80.54818973137105, 
              42.87867503532465
            ], 
            [
              80.53238456819332, 
              42.871440277247075
            ], 
            [
              80.52645104458009, 
              42.86872422754112
            ], 
            [
              80.52617557144555, 
              42.8685981308991
            ], 
            [
              80.47573937337341, 
              42.86407644307343
            ], 
            [
              80.40026693537084, 
              42.84327512504706
            ], 
            [
              80.40008507716465, 
              42.843225002232145
            ], 
            [
              80.38712968748513, 
              42.835172619221055
            ], 
            [
              80.38137820823778, 
              42.8315978050947
            ], 
            [
              80.33352583165185, 
              42.81725759526188
            ], 
            [
              80.31636925633615, 
              42.81583649375921
            ], 
            [
              80.28133263529293, 
              42.822967841492755
            ], 
            [
              80.26448611833973, 
              42.82384634063618
            ], 
            [
              80.24797226780595, 
              42.8164099788375
            ], 
            [
              80.24784630696155, 
              42.81635325769673
            ], 
            [
              80.22707238138537, 
              42.79118683550411
            ], 
            [
              80.2049548686723, 
              42.73129385063078
            ], 
            [
              80.18852176286913, 
              42.70178660776577
            ], 
            [
              80.15203820190158, 
              42.66057465249827
            ], 
            [
              80.14335656145619, 
              42.64499420831612
            ], 
            [
              80.13963585840821, 
              42.623135077122186
            ], 
            [
              80.14501020695553, 
              42.607322088943306
            ], 
            [
              80.15307173067589, 
              42.59176748318288
            ], 
            [
              80.16185672390873, 
              42.552570909519886
            ], 
            [
              80.1733288923146, 
              42.53709381812524
            ], 
            [
              80.19968387201317, 
              42.50856842719122
            ], 
            [
              80.21001915885716, 
              42.49105011666961
            ], 
            [
              80.211569451569, 
              42.478957831538764
            ], 
            [
              80.20588504465917, 
              42.46614207599606
            ], 
            [
              80.19430952346579, 
              42.4465050319817
            ], 
            [
              80.19575646339013, 
              42.43480031957915
            ], 
            [
              80.21818403536497, 
              42.35514109948218
            ], 
            [
              80.22521203031101, 
              42.339224758515854
            ], 
            [
              80.23513390510567, 
              42.324781195895525
            ], 
            [
              80.24908654131087, 
              42.310130926800866
            ], 
            [
              80.26789676302525, 
              42.23819733364007
            ], 
            [
              80.2600419448799, 
              42.216648260808654
            ], 
            [
              80.24871627153874, 
              42.20511666700065
            ], 
            [
              80.24867313016091, 
              42.205072740514595
            ], 
            [
              80.21013906996217, 
              42.18978756354528
            ], 
            [
              80.20991580606966, 
              42.18969900190746
            ], 
            [
              80.16609419179355, 
              42.208948472294196
            ], 
            [
              80.13612186093519, 
              42.2390758327835
            ], 
            [
              80.1096635275498, 
              42.27356985146753
            ], 
            [
              80.07659061036844, 
              42.30594513575949
            ], 
            [
              80.01178836494114, 
              42.34968923566976
            ], 
            [
              79.97354780478742, 
              42.3917021757149
            ], 
            [
              79.9598018732579, 
              42.403768622424025
            ], 
            [
              79.91753055169369, 
              42.424645900787766
            ], 
            [
              79.69604536350278, 
              42.460044257036884
            ], 
            [
              79.6522237483274, 
              42.46125865296449
            ], 
            [
              79.5715051610344, 
              42.44973480861455
            ], 
            [
              79.47590376154943, 
              42.4542048204961
            ], 
            [
              79.42515750511484, 
              42.46978526467825
            ], 
            [
              79.39797570221697, 
              42.49714793562879
            ], 
            [
              79.3526037943297, 
              42.57747894929412
            ], 
            [
              79.32087446518449, 
              42.60241282838939
            ], 
            [
              79.24180952339083, 
              42.62993052807144
            ], 
            [
              79.2059460791483, 
              42.656647243875284
            ], 
            [
              79.19178673736809, 
              42.6750182151186
            ], 
            [
              79.1814514505241, 
              42.69377675998953
            ], 
            [
              79.17566368992743, 
              42.71411143689335
            ], 
            [
              79.17473351394057, 
              42.73723663995901
            ], 
            [
              79.18041792174972, 
              42.77570974410946
            ], 
            [
              79.17287316286621, 
              42.78583832447913
            ], 
            [
              79.14786176940521, 
              42.79113515866072
            ], 
            [
              79.1082776221146, 
              42.785528266116614
            ], 
            [
              79.03045291556964, 
              42.7563569200359
            ], 
            [
              78.99252241377843, 
              42.75733877196683
            ], 
            [
              78.95386844247469, 
              42.768604234797635
            ], 
            [
              78.88761925622373, 
              42.77144643780292
            ], 
            [
              78.80762413934264, 
              42.795786037695564
            ], 
            [
              78.6865979352466, 
              42.804803574925074
            ], 
            [
              78.66954471181907, 
              42.811392320299376
            ], 
            [
              78.63502485561264, 
              42.8326830107124
            ], 
            [
              78.59389041561025, 
              42.85040802680902
            ], 
            [
              78.49570519373975, 
              42.87578115457666
            ], 
            [
              78.42914594912628, 
              42.88084544566084
            ], 
            [
              78.38511762927521, 
              42.87841665290625
            ], 
            [
              78.36424035001221, 
              42.8727322450971
            ], 
            [
              78.32786014183216, 
              42.85547231699388
            ], 
            [
              78.31080691930396, 
              42.850692246749816
            ], 
            [
              78.28982628815271, 
              42.8516482611584
            ], 
            [
              78.248691847251, 
              42.862603664727374
            ], 
            [
              78.22926150881165, 
              42.86523916305697
            ], 
            [
              78.1831661314119, 
              42.860355740025454
            ], 
            [
              78.13748416516216, 
              42.86219025357741
            ], 
            [
              78.03030724448382, 
              42.85490387621297
            ], 
            [
              77.98576215979591, 
              42.86038157844712
            ], 
            [
              77.92891808440214, 
              42.885186265433845
            ], 
            [
              77.90659386611406, 
              42.89146495244563
            ], 
            [
              77.88344282462668, 
              42.89345449472921
            ], 
            [
              77.86070519428932, 
              42.89102570287395
            ], 
            [
              77.85181684736966, 
              42.88818349896934
            ], 
            [
              77.8351770368908, 
              42.880018622461535
            ], 
            [
              77.80954552580545, 
              42.87144033480365
            ], 
            [
              77.79776329903706, 
              42.877693183393774
            ], 
            [
              77.79125206892792, 
              42.883248399094384
            ], 
            [
              77.78711795472987, 
              42.88994049725619
            ], 
            [
              77.78081342929636, 
              42.895805772218694
            ], 
            [
              77.7135307151704, 
              42.907768866140316
            ], 
            [
              77.6472815289195, 
              42.909680894957376
            ], 
            [
              77.62650760244395, 
              42.90673533826532
            ], 
            [
              77.57410770051001, 
              42.88805430776017
            ], 
            [
              77.55736453634432, 
              42.88833852770097
            ], 
            [
              77.53803755069248, 
              42.89647756578711
            ], 
            [
              77.52057091701425, 
              42.9070970725719
            ], 
            [
              77.50124393136241, 
              42.91474518514224
            ], 
            [
              77.46134972481002, 
              42.91459015551135
            ], 
            [
              77.4335478042878, 
              42.921618150457334
            ], 
            [
              77.41814822815826, 
              42.922393296813254
            ], 
            [
              77.40295535670441, 
              42.91993866653627
            ], 
            [
              77.36047732956519, 
              42.9047199566607
            ], 
            [
              77.3276111188581, 
              42.89779531540154
            ], 
            [
              77.2292191914126, 
              42.90999095331989
            ], 
            [
              77.21181652381358, 
              42.910121212923684
            ], 
            [
              77.1946993343069, 
              42.910249335738285
            ], 
            [
              77.178266229403, 
              42.91342743552781
            ], 
            [
              77.16328006352416, 
              42.922186591238244
            ], 
            [
              77.13465132070195, 
              42.95195221652165
            ], 
            [
              77.12348921065859, 
              42.95908356425514
            ], 
            [
              77.08948611838969, 
              42.96835948300378
            ], 
            [
              76.97610802596466, 
              42.98238963447409
            ], 
            [
              76.9564709819503, 
              42.988694159907595
            ], 
            [
              76.93693729072345, 
              42.986213691208945
            ], 
            [
              76.89724979064539, 
              42.97471568438141
            ], 
            [
              76.85301476432, 
              42.97432811165311
            ], 
            [
              76.83308978256747, 
              42.971953631654856
            ], 
            [
              76.8330676610438, 
              42.971950995741906
            ], 
            [
              76.82986239273527, 
              42.970245518715785
            ], 
            [
              76.81381389189767, 
              42.96170634257368
            ], 
            [
              76.8137406753919, 
              42.96166738574129
            ], 
            [
              76.79264097220317, 
              42.94334666681527
            ], 
            [
              76.7925533386657, 
              42.94327057517694
            ], 
            [
              76.78490522699468, 
              42.9398599313908
            ], 
            [
              76.77911746639802, 
              42.93949819618484
            ], 
            [
              76.760927362308, 
              42.94228872324601
            ], 
            [
              76.75368477023602, 
              42.941006181190346
            ], 
            [
              76.75348595531267, 
              42.9409709745309
            ], 
            [
              76.75121219308829, 
              42.93727610900527
            ], 
            [
              76.74997195873897, 
              42.93278025960137
            ], 
            [
              76.74589214290813, 
              42.92915942356859
            ], 
            [
              76.74583784364165, 
              42.92911123339678
            ], 
            [
              76.70749393070042, 
              42.91389252352121
            ], 
            [
              76.68837365062353, 
              42.91050771725742
            ], 
            [
              76.64393191962245, 
              42.91133454045672
            ], 
            [
              76.6053813011062, 
              42.89872549048903
            ], 
            [
              76.5846073746307, 
              42.89500478744105
            ], 
            [
              76.55835574771965, 
              42.89841543212657
            ], 
            [
              76.50647260972323, 
              42.9146935082988
            ], 
            [
              76.48011762912535, 
              42.9171739769975
            ], 
            [
              76.46168340136796, 
              42.9112340592045
            ], 
            [
              76.46151411298598, 
              42.91117951082583
            ], 
            [
              76.43467514963851, 
              42.89195575565367
            ], 
            [
              76.43164513581445, 
              42.88978546852462
            ], 
            [
              76.41366173729938, 
              42.88570303027069
            ], 
            [
              76.40415327365469, 
              42.889475409262786
            ], 
            [
              76.39278445803637, 
              42.905469265494276
            ], 
            [
              76.3825525248792, 
              42.910249335738285
            ], 
            [
              76.37066694532331, 
              42.90978424774488
            ], 
            [
              76.35071984204711, 
              42.903117988004794
            ], 
            [
              76.34007449773992, 
              42.90190359117787
            ], 
            [
              76.25408491378778, 
              42.92133392961722
            ], 
            [
              76.16334109891267, 
              42.92133392961722
            ], 
            [
              76.09027062329068, 
              42.93443390600004
            ], 
            [
              76.06412234916712, 
              42.93417552358159
            ], 
            [
              75.99880333890303, 
              42.91784577056592
            ], 
            [
              75.97616906135318, 
              42.918930976183674
            ], 
            [
              75.89762088439636, 
              42.93588084592437
            ], 
            [
              75.85855350104327, 
              42.94001496012237
            ], 
            [
              75.80677371583437, 
              42.93696605064275
            ], 
            [
              75.80659904950659, 
              42.93708565867627
            ], 
            [
              75.77349409397732, 
              42.95975535782355
            ], 
            [
              75.58260135247048, 
              42.98027090098134
            ], 
            [
              75.65112430184513, 
              43.01706452121073
            ], 
            [
              75.56813195142848, 
              43.07049795191898
            ], 
            [
              75.45154992079227, 
              43.10620636653067
            ], 
            [
              75.36535363126512, 
              43.15777944616457
            ], 
            [
              75.3355880068811, 
              43.19508983033148
            ], 
            [
              75.32215213371404, 
              43.21989451731815
            ], 
            [
              75.31398725810556, 
              43.25183055293775
            ], 
            [
              75.29714074115236, 
              43.29771922476249
            ], 
            [
              75.36028934108026, 
              43.39673126893297
            ], 
            [
              75.42819217283056, 
              43.46848399494047
            ], 
            [
              75.34395958896391, 
              43.5033397488304
            ], 
            [
              75.2542493019638, 
              43.50359813124879
            ], 
            [
              75.22262332560604, 
              43.533725490838776
            ], 
            [
              75.18324588389049, 
              43.52230499927634
            ], 
            [
              75.10263064938499, 
              43.53643850353416
            ], 
            [
              75.01798465346906, 
              43.56271596976626
            ], 
            [
              75.27295617089061, 
              43.87711538316847
            ], 
            [
              75.31843143066607, 
              43.966903184534374
            ], 
            [
              75.32649295438637, 
              44.07834341061994
            ], 
            [
              75.24722130701775, 
              44.151155503823475
            ], 
            [
              75.14882938047157, 
              44.22076365791651
            ], 
            [
              74.97860721265278, 
              44.291121120843115
            ], 
            [
              74.75867231627444, 
              44.31341950160879
            ], 
            [
              74.61056766116866, 
              44.412870795350955
            ], 
            [
              74.55744428882292, 
              44.5166629097655
            ], 
            [
              74.53956424309541, 
              44.655336615592375
            ], 
            [
              74.15560835154423, 
              44.907595119419284
            ], 
            [
              74.11158003079385, 
              44.97363760009523
            ], 
            [
              74.09463016105315, 
              45.05993724240989
            ], 
            [
              73.99747846885629, 
              45.075853583376215
            ], 
            [
              73.89981001182264, 
              45.07763642008479
            ], 
            [
              73.81320031114552, 
              45.172178453273034
            ], 
            [
              73.8467899922644, 
              45.2583230659568
            ], 
            [
              74.09411339711562, 
              45.269330145469894
            ], 
            [
              74.07065229726578, 
              45.3168724636933
            ], 
            [
              74.05308230990073, 
              45.3708226592384
            ], 
            [
              74.03044803235088, 
              45.53582550724144
            ], 
            [
              74.05638960179874, 
              45.776792710715085
            ], 
            [
              74.18434044805332, 
              45.955851548610156
            ], 
            [
              74.76187625538495, 
              46.39951955788132
            ], 
            [
              75.40276736821954, 
              46.679476630342265
            ], 
            [
              75.63613813686555, 
              46.66994232827591
            ], 
            [
              75.8959672379977, 
              46.68996694591789
            ], 
            [
              76.16096398300147, 
              46.681259467050836
            ], 
            [
              76.3284989765466, 
              46.64989187311153
            ], 
            [
              76.38213911282986, 
              46.654801133665444
            ], 
            [
              76.39030398933767, 
              46.64624868442928
            ], 
            [
              76.40208621610606, 
              46.644595038030616
            ], 
            [
              76.40704715350341, 
              46.66263011338907
            ], 
            [
              76.49024620949501, 
              46.62909210911357
            ], 
            [
              76.51040001834622, 
              46.61519114885249
            ], 
            [
              76.52021854035343, 
              46.613589179297264
            ], 
            [
              76.52435265455142, 
              46.6253714060656
            ], 
            [
              76.52466271381326, 
              46.639427395058306
            ], 
            [
              76.52600630095009, 
              46.646171170063496
            ], 
            [
              76.53003706236058, 
              46.6501244171082
            ], 
            [
              76.53809858608093, 
              46.655782985596375
            ], 
            [
              76.54802046087565, 
              46.660950629468005
            ], 
            [
              76.5972164245984, 
              46.67575592729429
            ], 
            [
              76.6096187680917, 
              46.675032456882434
            ], 
            [
              76.66057173010131, 
              46.66604075807459
            ], 
            [
              76.68196577330184, 
              46.66578237565619
            ], 
            [
              76.7016028173162, 
              46.67115672420351
            ], 
            [
              76.72237674379176, 
              46.683714097327766
            ], 
            [
              76.72826785717592, 
              46.67529083930083
            ], 
            [
              76.73002485546277, 
              46.66547231729368
            ], 
            [
              76.72630415241474, 
              46.65624807358978
            ], 
            [
              76.71555545442072, 
              46.64958181384969
            ], 
            [
              76.73012820825028, 
              46.63141754818133
            ], 
            [
              76.75741336483497, 
              46.617852484704486
            ], 
            [
              76.85053429562129, 
              46.59157501847238
            ], 
            [
              76.90737837101506, 
              46.56801056583498
            ], 
            [
              76.93528364432478, 
              46.560207424533075
            ], 
            [
              76.90975548692626, 
              46.585425523569086
            ], 
            [
              76.86831098856135, 
              46.618007514335375
            ], 
            [
              76.83286095546879, 
              46.65252737054175
            ], 
            [
              76.82541954937278, 
              46.683714097327766
            ], 
            [
              76.84019900877729, 
              46.69074209227381
            ], 
            [
              76.86159305197782, 
              46.68169871662252
            ], 
            [
              76.9113057796381, 
              46.640719306251015
            ], 
            [
              76.92040083213277, 
              46.63679189672871
            ], 
            [
              76.9321830589011, 
              46.63529328086025
            ], 
            [
              76.94417199124445, 
              46.63596507442867
            ], 
            [
              76.96939009028051, 
              46.642114569331966
            ], 
            [
              77.01920617072824, 
              46.64686880115431
            ], 
            [
              77.06271772664184, 
              46.63560333922277
            ], 
            [
              77.10075158032123, 
              46.61051443139593
            ], 
            [
              77.13392785029009, 
              46.573850002375764
            ], 
            [
              77.13547814300193, 
              46.566150213861306
            ], 
            [
              77.13258426315326, 
              46.55994904211468
            ], 
            [
              77.1340312030776, 
              46.554006252786394
            ], 
            [
              77.14819054575713, 
              46.54718496341536
            ], 
            [
              77.15966271326369, 
              46.54661652263445
            ], 
            [
              77.22766889870076, 
              46.55855377903373
            ], 
            [
              77.24048465334414, 
              46.5711628281021
            ], 
            [
              77.25050988182562, 
              46.58682078754936
            ], 
            [
              77.26363569573084, 
              46.60118683490458
            ], 
            [
              77.28358279810772, 
              46.61175466574531
            ], 
            [
              77.30704389885688, 
              46.617981675913654
            ], 
            [
              77.38920942607422, 
              46.623588568457706
            ], 
            [
              77.46290001842118, 
              46.642114569331966
            ], 
            [
              77.49163211493021, 
              46.640176703891825
            ], 
            [
              77.51199262845711, 
              46.64883250591549
            ], 
            [
              77.5996358579086, 
              46.67575592729429
            ], 
            [
              77.61110802631441, 
              46.816651719401364
            ], 
            [
              77.58092898988104, 
              47.17484691045661
            ], 
            [
              77.65585981657733, 
              47.201925360566975
            ], 
            [
              77.85109337785718, 
              47.179807847853965
            ], 
            [
              77.94803836447898, 
              47.23179433863788
            ], 
            [
              78.04622358634947, 
              47.25964793600349
            ], 
            [
              78.11009565668928, 
              47.21386261696625
            ], 
            [
              78.27525353342389, 
              47.304296373478905
            ]
          ]
        ]
      }, 
      "type": "Feature", 
      "properties": {
        "ne:ProvNumber": 2000, 
        "alias_SWE_Q": [
          "Alma-Ata"
        ], 
        "hierarchy": [
          "woe:state=20070180", 
          "woe:country=23424871", 
          "woe:planet=1"
        ], 
        "ne_latitude": 47.304296373478905, 
        "ne:Shape_Area": 25.3398050467, 
        "placetype": "state", 
        "ne:Country_Pr": null, 
        "ne:VALIDFR_1": "19970422", 
        "alias_KOR_Q": [
          "\uc54c\ub9c8\ud2f0"
        ], 
        "ne:gadm_level": 1.0, 
        "ne:ADM0_A3": "KAZ", 
        "ne:ScaleRank": 4, 
        "alias_CHI_Q": [
          "\u963f\u62c9\u6728\u56fe"
        ], 
        "ne:DataRank": 6, 
        "alias_JPN_Q": [
          "\u30a2\u30eb\u30de\u30c8\u30a4"
        ], 
        "ne:Abbrev": null, 
        "ne:VALIDTO_1": "Present", 
        "sw_longitude": 73.81320031114552, 
        "adjacent": [
          "woe:state=20070179", 
          "woe:state=20070195", 
          "woe:state=20070178", 
          "woe:state=20070175", 
          "woe:state=20070190", 
          "woe:state=2345983", 
          "woe:state=12578003"
        ], 
        "provider": "geoplanet 7.6.0", 
        "latitude": 44.714, 
        "ne:FIPS_1": "KZ01", 
        "ne:FIRST_FIPS": null, 
        "ne:FIRST_HASC": null, 
        "ne:ENGTYPE_1": "Region", 
        "sw_latitude": 42.18969900190746, 
        "lang": "ENG", 
        "ne:MAP_COLOR": 1, 
        "ne:OBJECTID": 3207, 
        "ne:Postal": "AA", 
        "ne:Region_Cod": "KAZ-TKG", 
        "ne:VARNAME_1": "Alma-Ata|Alma-Atinskaya Oblast'|Almatinskaya Oblast'", 
        "ne:ISO": "KAZ", 
        "ne:TYPE_1": "Oblasy", 
        "ne:Region_C_2": null, 
        "ne:Shape_Leng": 28.2846271521, 
        "ne:CheckMe": 0, 
        "ne:NAME_0": "Kazakhstan", 
        "ne:NAME_1": "Almaty", 
        "ne:Region_C_1": null, 
        "ne:Region_C_3": null, 
        "ne:LabelRank": 6, 
        "ne:Area_sqkm": 222133.3, 
        "woe:id": "20070180", 
        "name": "Almaty", 
        "ne:VertexCou": 431.0, 
        "adjacent_woeid": [
          2345983, 
          12578003, 
          20070175, 
          20070178, 
          20070179, 
          20070190, 
          20070195
        ], 
        "ne:HASC_1": "KZ.AA", 
        "ne:REMARKS_1": null, 
        "ne_longitude": 82.63602094930741, 
        "longitude": 78.016, 
        "iso": "KZ", 
        "date_indexed": "2010-12-02T08:54:03Z", 
        "ne:NL_NAME_1": null, 
        "fullname": "Almaty, Kazakhstan", 
        "ne:Region": "Taldy Kurgan", 
        "ne:NEV_Countr": "Kazakhstan", 
        "ne:RegionVar": null, 
        "ne:sameAsCity": 6
      }, 
      "id": 20070180
    }
  ], 
  "bbox": [
    73.81320031114552, 
    42.18969900190746, 
    82.63602094930741, 
    47.304296373478905
  ]
}